[
 {"q": "Docker Compose nima uchun?", "options": ["Ko'p konteynerli ilovani bitta YAML bilan boshqarish", "Image qurish", "Faqat tarmoq", "Log ko'rish"], "correct": 0, "difficulty": 1, "explanation": "Compose — bir nechta servisni bitta docker-compose.yml'да ta'riflab boshqaradi."},
 {"q": "Compose konfiguratsiya fayli nomi?", "options": ["docker-compose.yml (yoki compose.yaml)", "Dockerfile", "compose.txt", "docker.json"], "correct": 0, "difficulty": 1, "explanation": "docker-compose.yml / compose.yaml — YAML formatда."},
 {"q": "Compose faylда har bir konteyner nima deyiladi?", "options": ["service", "image", "volume", "network"], "correct": 0, "difficulty": 1, "explanation": "Har konteyner — 'services:' ostidagi bitta service."},
 {"q": "Butun stackни fonda ko'tarish?", "options": ["docker compose up -d", "docker run -d", "docker start", "docker build"], "correct": 0, "difficulty": 1, "explanation": "docker compose up -d — barcha servisни fonda ishga tushiradi."},
 {"q": "Butun stackни to'xtatib o'chirish?", "options": ["docker compose down", "docker stop", "docker rm", "docker kill"], "correct": 0, "difficulty": 1, "explanation": "docker compose down — konteyner + tarmoqni tozalaydi."},
 {"q": "Stack holatini ko'rish?", "options": ["docker compose ps", "docker ps -a", "docker images", "docker stats"], "correct": 0, "difficulty": 1, "explanation": "docker compose ps — shu stack servislari holatini ko'rsatadi."},
 {"q": "Barcha servis loglarini ko'rish?", "options": ["docker compose logs", "docker logs", "cat logs", "docker ps"], "correct": 0, "difficulty": 1, "explanation": "docker compose logs — stackдагi hamma servis loglarini birga ko'rsatadi."},
 {"q": "Compose'да servisни image'дан olish?", "options": ["image: nginx:alpine", "from: nginx", "run: nginx", "use: nginx"], "correct": 0, "difficulty": 1, "explanation": "image: — tayyor image'dan servis yaratadi."},
 {"q": "Compose'да Dockerfile'дан qurish?", "options": ["build: .", "image: .", "make: .", "run: ."], "correct": 0, "difficulty": 2, "explanation": "build: . — joriy papkadagi Dockerfile'дан image quradi (Day-16)."},
 {"q": "Compose'да port ochish?", "options": ["ports: - \"8080:80\"", "expose 8080", "-p 8080", "port=8080"], "correct": 0, "difficulty": 2, "explanation": "ports: ro'yxati — host:konteyner xaritasi."},
 {"q": "Compose'да doimiy ma'lumot?", "options": ["volumes: bo'limi", "data: bo'limi", "disk:", "save:"], "correct": 0, "difficulty": 2, "explanation": "volumes: — Day-17 dagi doimiy ma'lumot (DB v.h.)."},
 {"q": "depends_on nima qiladi?", "options": ["Servis qaysi boshqasidan keyin ishga tushishini belgilaydi", "Portni ochadi", "Image quradi", "Volume yaratadi"], "correct": 0, "difficulty": 2, "explanation": "depends_on — ishga tushish tartibini belgilaydi (db, keyin web)."},
 {"q": "Compose stackдagi servislar bir-birini qanday topadi?", "options": ["Service NOMI bilan (avtomatik tarmoq + DNS)", "Faqat IP", "Topa olmaydi", "MAC bilan"], "correct": 0, "difficulty": 2, "explanation": "Compose avtomatik tarmoq yaratadi; servislar nom bilan ulanadi (web -> db)."},
 {"q": "Compose `up` paytida tarmoq nima bo'ladi?", "options": ["Avtomatik yaratiladi (qo'lда kerak emas)", "Yaratilmaydi", "Faqat -p bilan", "Host tarmog'i"], "correct": 0, "difficulty": 2, "explanation": "Compose stack uchun default tarmoq o'zi yaratiladi."},
 {"q": "Compose'да servisning ishga tushish buyrug'ini o'zgartirish?", "options": ["command: sleep 600", "cmd: sleep", "run: sleep", "exec: sleep"], "correct": 0, "difficulty": 2, "explanation": "command: — image'ning default CMD'ini almashtiradi."},
 {"q": "Servis ичiga buyruq bilan kirish?", "options": ["docker compose exec web sh", "docker exec compose", "compose enter", "docker compose run-in"], "correct": 0, "difficulty": 2, "explanation": "docker compose exec <servis> <buyruq> — ishlab turgan servis ичida."},
 {"q": "`docker compose down -v` dagi -v nima?", "options": ["Volume'larni ham o'chiradi", "Verbose", "Versiya", "Tezkor"], "correct": 0, "difficulty": 3, "explanation": "-v — stack volume'larini ham tozalaydi (ma'lumot ham ketadi)."},
 {"q": "Compose'ning asosiy afzalligi?", "options": ["Bitta buyruq bilan butun stack (tarmoq+volume+servis)", "Tezroq internet", "Kamroq RAM", "Image kichrayadi"], "correct": 0, "difficulty": 2, "explanation": "Ko'p docker run o'rniga bitta up — hammasi avtomatik."},
 {"q": "YAML'да servislar ro'yxati qanday tuziladi?", "options": ["services: ostida har biri kalit (web:, db:)", "services: - web - db", "[web, db]", "service1, service2"], "correct": 0, "difficulty": 2, "explanation": "services: ostида har servis o'z nomi (kalit) bilan, indentatsiya bilan."},
 {"q": "Ikki servis (web, db) bir compose'да — necha buyruq bilan ko'tariladi?", "options": ["Bitta: docker compose up", "Ikkita run", "Har biriga alohida", "Uchta"], "correct": 0, "difficulty": 1, "explanation": "Bitta `up` — barcha servis birga ko'tariladi."},
 {"q": "Compose'да environment (muhit o'zgaruvchi)?", "options": ["environment: - KEY=value", "env KEY", "set KEY", "ENV: KEY"], "correct": 0, "difficulty": 2, "explanation": "environment: — servisга muhit o'zgaruvchilarini beradi."},
 {"q": "`web` ичidan `db` ga ulanish manzili?", "options": ["db (servis nomi) — masalan http://db:5432", "localhost", "127.0.0.1", "0.0.0.0"], "correct": 0, "difficulty": 3, "explanation": "Servis nomi host vazifasini bajaradi (compose DNS)."},
 {"q": "Compose faylни o'zgartirgach yangilash?", "options": ["docker compose up -d (qayta qo'llaydi)", "Hech narsa", "restart server", "rm -rf"], "correct": 0, "difficulty": 2, "explanation": "up -d — o'zgargan servislarni qayta yaratadi."},
 {"q": "Faqat bitta servisни qayta ishga tushirish?", "options": ["docker compose restart web", "docker restart all", "compose reload", "up --one"], "correct": 0, "difficulty": 2, "explanation": "docker compose restart <servis> — faqat o'shani qayta yuradi."},
 {"q": "Compose stack uchun loyiha nomi (-p) nima beradi?", "options": ["Stackни alohida nomlaydi (konteynerlar shu prefiks bilan)", "Portni belgilaydi", "Volume nomi", "Image tegi"], "correct": 0, "difficulty": 3, "explanation": "-p <nom> — loyiha nomi; konteynerlar <nom>-<servis>-1 ko'rinishida."},
 {"q": "Compose qaysi Day ko'nikmalarini birlashtiradi?", "options": ["run(15)+build(16)+volume/network(17) — hammasi YAML'да", "Faqat git", "Faqat nginx", "Hech biri"], "correct": 0, "difficulty": 3, "explanation": "Compose — image/build, volume, network, port — bari bitta faylда."},
 {"q": "`docker compose up` (-d siz) nima qiladi?", "options": ["Stackни ko'tarib, loglarni ekranда ko'rsatadi (fon emas)", "O'chiradi", "Faqat quradi", "Hech narsa"], "correct": 0, "difficulty": 2, "explanation": "-d siz — terminal band bo'ladi, loglar oqadi (Ctrl+C to'xtatadi)."},
 {"q": "Stackdagi servislar sonini ko'paytirish (masshtab)?", "options": ["docker compose up -d --scale web=3", "docker scale 3", "up x3", "compose copy"], "correct": 0, "difficulty": 3, "explanation": "--scale <servis>=N — bir servisning N nusxasini ishga tushiradi."},
 {"q": "Compose volumesiz DB konteyner o'chsa — ma'lumot?", "options": ["Yo'qoladi (volume kerak edi)", "Saqlanadi", "Image'ga ketadi", "Avtomatik backup"], "correct": 0, "difficulty": 2, "explanation": "Volumesiz — Day-17 dagidek ma'lumot yo'qoladi; volumes: qo'shish kerak."},
 {"q": "'Bitta buyruq bilan API + DB + cache' — qaysi vosita?", "options": ["Docker Compose", "Bitta Dockerfile", "docker run", "git"], "correct": 0, "difficulty": 1, "explanation": "Compose — ko'p servisli ilovani bitta `up` bilan ko'taradi."}
]
